atriage/__init__.py
atriage/asan.py
atriage/cli.py
atriage/db.py
atriage/exploitable.py
atriage/utils.py
atriage/collectors/__init__.py
atriage/collectors/afl.py
atriage/collectors/exceptions.py
atriage/collectors/flatdir.py
atriage/collectors/interface.py
atriage-0.3.dist-info/LICENSE.txt
atriage-0.3.dist-info/METADATA
atriage-0.3.dist-info/WHEEL
atriage-0.3.dist-info/entry_points.txt
atriage-0.3.dist-info/top_level.txt
atriage-0.3.dist-info/RECORD
