Metadata-Version: 2.1
Name: atriage
Version: 0.3
Summary: A dumb afl-fuzz triage tool.
Home-page: https://github.com/Ayrx/atriage
Author: Terry Chia
Author-email: terrycwk1994@gmail.com
License: Apache License, Version 2.0
Platform: UNKNOWN
Requires-Python: >=3
Requires-Dist: Click
Requires-Dist: tabulate
